LICENSE
setup.py
ReneTelegramBot/__init__.py
ReneTelegramBot.egg-info/PKG-INFO
ReneTelegramBot.egg-info/SOURCES.txt
ReneTelegramBot.egg-info/dependency_links.txt
ReneTelegramBot.egg-info/top_level.txt
ReneTelegramBot/Clases/BotConversation.py
ReneTelegramBot/Clases/TBClases.py
ReneTelegramBot/Clases/__init__.py
ReneTelegramBot/Utiles/TBUtiles.py
ReneTelegramBot/Utiles/__init__.py